pybe/__init__.py
pybe/benchmark.py
pybe/wrappers.py
pybe-1.0.0.dist-info/LICENSE.txt
pybe-1.0.0.dist-info/METADATA
pybe-1.0.0.dist-info/WHEEL
pybe-1.0.0.dist-info/top_level.txt
pybe-1.0.0.dist-info/RECORD
