Metadata-Version: 2.1
Name: pybe
Version: 1.0.0
Summary: Benchmarking python functions
Author: Nicolai Palm
Author-email: nicolaipalm@googlemail.com
License: MIT
Classifier: Programming Language :: Python :: 3
Classifier: License :: OSI Approved :: MIT License
Classifier: Operating System :: OS Independent
Requires-Python: >=3.9
License-File: LICENSE.txt
Requires-Dist: numpy
Requires-Dist: plotly
Requires-Dist: tqdm
Requires-Dist: pandas
Provides-Extra: dev
Requires-Dist: pre-commit ; extra == 'dev'
Requires-Dist: flake8 ; extra == 'dev'
Requires-Dist: flake8-print ; extra == 'dev'
Provides-Extra: test
Requires-Dist: pytest ; extra == 'test'
Requires-Dist: pytest-cov ; extra == 'test'
